MANIFEST.in
setup.py
drugstandards/__init__.py
drugstandards.egg-info/PKG-INFO
drugstandards.egg-info/SOURCES.txt
drugstandards.egg-info/dependency_links.txt
drugstandards.egg-info/not-zip-safe
drugstandards.egg-info/requires.txt
drugstandards.egg-info/top_level.txt
drugstandards/data/synonyms.dat