Metadata-Version: 1.0
Name: drugstandards
Version: 0.3
Summary: Tools for standardizing drug names.
Home-page: http://github.com/mlbernauer/drugstandards
Author: Michael L. Bernauer
Author-email: mlbernauer@gmail.com
License: MIT
Platform: UNKNOWN
